setup.cfg
setup.py
IPyMongo.egg-info/PKG-INFO
IPyMongo.egg-info/SOURCES.txt
IPyMongo.egg-info/dependency_links.txt
IPyMongo.egg-info/entry_points.txt
IPyMongo.egg-info/not-zip-safe
IPyMongo.egg-info/requires.txt
IPyMongo.egg-info/top_level.txt
ipymongo/__init__.py
ipymongo/main.py
scripts/ipymongo