Metadata-Version: 1.0
Name: IPyMongo
Version: 0.0dev-20120913
Summary: IPython extension and wrapper for using with MongoDB
Home-page: UNKNOWN
Author: Rick Copeland
Author-email: rick@arborian.com
License: Apache
Platform: UNKNOWN
